LICENSE.txt
README.md
setup.py
pandas_dataset/__init__.py
pandas_dataset/column_types.py
pandas_dataset/dataset.py
pandas_dataset/dataset_hash_check.py
pandas_dataset/indexes.py
pandas_dataset/internal.py
pandas_dataset/merge.py
pandas_dataset/stats.py
pandas_dataset/torch_dataset.py
pandas_dataset/utils.py
pandas_dataset.egg-info/PKG-INFO
pandas_dataset.egg-info/SOURCES.txt
pandas_dataset.egg-info/dependency_links.txt
pandas_dataset.egg-info/requires.txt
pandas_dataset.egg-info/top_level.txt
pandas_dataset/input_output/__init__.py
pandas_dataset/input_output/csv_read.py
pandas_dataset/input_output/csv_write.py
pandas_dataset/input_output/parquet_read.py
pandas_dataset/input_output/parquet_write.py