Metadata-Version: 2.1
Name: pandas-dataset
Version: 0.1.4
Summary: Python Datasets on top of Pandas
Home-page: https://gitlab.com/meehai/pandas-dataset
License: WTFPL
Requires-Python: >=3.8
License-File: LICENSE.txt
Requires-Dist: pandas==2.0.1
Requires-Dist: numpy<2.0.0,>=1.24.1
Requires-Dist: loggez==0.3
Requires-Dist: pyarrow==11.0.0
Requires-Dist: natsort==8.4.0
Requires-Dist: lovely-tensors==0.1.15
Requires-Dist: torch>=2.2.1
